<annotation>
	<folder>videoframes</folder>
	<filename>0990ed11-55be-4bc9-9e6a-65eef9c08913.png</filename>
	<path>/home/will/Desktop/project/videoframes/0990ed11-55be-4bc9-9e6a-65eef9c08913.png</path>
	<source>
		<database>Unknown</database>
	</source>
	<size>
		<width>1280</width>
		<height>720</height>
		<depth>3</depth>
	</size>
	<segmented>0</segmented>
	<object>
		<name>player</name>
		<pose>Unspecified</pose>
		<truncated>0</truncated>
		<difficult>0</difficult>
		<bndbox>
			<xmin>198</xmin>
			<ymin>232</ymin>
			<xmax>314</xmax>
			<ymax>524</ymax>
		</bndbox>
	</object>
	<object>
		<name>player</name>
		<pose>Unspecified</pose>
		<truncated>0</truncated>
		<difficult>0</difficult>
		<bndbox>
			<xmin>1026</xmin>
			<ymin>215</ymin>
			<xmax>1138</xmax>
			<ymax>538</ymax>
		</bndbox>
	</object>
	<object>
		<name>player</name>
		<pose>Unspecified</pose>
		<truncated>0</truncated>
		<difficult>0</difficult>
		<bndbox>
			<xmin>1109</xmin>
			<ymin>198</ymin>
			<xmax>1236</xmax>
			<ymax>514</ymax>
		</bndbox>
	</object>
</annotation>
