<annotation>
	<folder>videoframes</folder>
	<filename>13f1f959-a39c-4e74-81f7-9f684ee11473.png</filename>
	<path>/home/will/Desktop/project/videoframes/13f1f959-a39c-4e74-81f7-9f684ee11473.png</path>
	<source>
		<database>Unknown</database>
	</source>
	<size>
		<width>1280</width>
		<height>720</height>
		<depth>3</depth>
	</size>
	<segmented>0</segmented>
	<object>
		<name>ball</name>
		<pose>Unspecified</pose>
		<truncated>0</truncated>
		<difficult>0</difficult>
		<bndbox>
			<xmin>640</xmin>
			<ymin>367</ymin>
			<xmax>695</xmax>
			<ymax>415</ymax>
		</bndbox>
	</object>
	<object>
		<name>player</name>
		<pose>Unspecified</pose>
		<truncated>1</truncated>
		<difficult>0</difficult>
		<bndbox>
			<xmin>1035</xmin>
			<ymin>614</ymin>
			<xmax>1154</xmax>
			<ymax>720</ymax>
		</bndbox>
	</object>
	<object>
		<name>player</name>
		<pose>Unspecified</pose>
		<truncated>0</truncated>
		<difficult>0</difficult>
		<bndbox>
			<xmin>527</xmin>
			<ymin>214</ymin>
			<xmax>624</xmax>
			<ymax>433</ymax>
		</bndbox>
	</object>
	<object>
		<name>player</name>
		<pose>Unspecified</pose>
		<truncated>0</truncated>
		<difficult>0</difficult>
		<bndbox>
			<xmin>553</xmin>
			<ymin>97</ymin>
			<xmax>653</xmax>
			<ymax>285</ymax>
		</bndbox>
	</object>
	<object>
		<name>player</name>
		<pose>Unspecified</pose>
		<truncated>1</truncated>
		<difficult>0</difficult>
		<bndbox>
			<xmin>492</xmin>
			<ymin>1</ymin>
			<xmax>577</xmax>
			<ymax>112</ymax>
		</bndbox>
	</object>
	<object>
		<name>player</name>
		<pose>Unspecified</pose>
		<truncated>1</truncated>
		<difficult>0</difficult>
		<bndbox>
			<xmin>371</xmin>
			<ymin>1</ymin>
			<xmax>468</xmax>
			<ymax>155</ymax>
		</bndbox>
	</object>
	<object>
		<name>player</name>
		<pose>Unspecified</pose>
		<truncated>0</truncated>
		<difficult>0</difficult>
		<bndbox>
			<xmin>273</xmin>
			<ymin>100</ymin>
			<xmax>409</xmax>
			<ymax>312</ymax>
		</bndbox>
	</object>
	<object>
		<name>player</name>
		<pose>Unspecified</pose>
		<truncated>0</truncated>
		<difficult>0</difficult>
		<bndbox>
			<xmin>159</xmin>
			<ymin>220</ymin>
			<xmax>295</xmax>
			<ymax>436</ymax>
		</bndbox>
	</object>
	<object>
		<name>player</name>
		<pose>Unspecified</pose>
		<truncated>1</truncated>
		<difficult>0</difficult>
		<bndbox>
			<xmin>1</xmin>
			<ymin>437</ymin>
			<xmax>114</xmax>
			<ymax>670</ymax>
		</bndbox>
	</object>
	<object>
		<name>player</name>
		<pose>Unspecified</pose>
		<truncated>0</truncated>
		<difficult>0</difficult>
		<bndbox>
			<xmin>121</xmin>
			<ymin>11</ymin>
			<xmax>233</xmax>
			<ymax>234</ymax>
		</bndbox>
	</object>
</annotation>
