<annotation>
	<folder>videoframes</folder>
	<filename>1e632216-9b64-4700-ab1f-0ff97a246053.png</filename>
	<path>/home/will/Desktop/project/videoframes/1e632216-9b64-4700-ab1f-0ff97a246053.png</path>
	<source>
		<database>Unknown</database>
	</source>
	<size>
		<width>1280</width>
		<height>720</height>
		<depth>3</depth>
	</size>
	<segmented>0</segmented>
	<object>
		<name>player</name>
		<pose>Unspecified</pose>
		<truncated>0</truncated>
		<difficult>0</difficult>
		<bndbox>
			<xmin>281</xmin>
			<ymin>271</ymin>
			<xmax>365</xmax>
			<ymax>516</ymax>
		</bndbox>
	</object>
	<object>
		<name>player</name>
		<pose>Unspecified</pose>
		<truncated>0</truncated>
		<difficult>0</difficult>
		<bndbox>
			<xmin>665</xmin>
			<ymin>72</ymin>
			<xmax>765</xmax>
			<ymax>287</ymax>
		</bndbox>
	</object>
	<object>
		<name>player</name>
		<pose>Unspecified</pose>
		<truncated>0</truncated>
		<difficult>0</difficult>
		<bndbox>
			<xmin>473</xmin>
			<ymin>348</ymin>
			<xmax>641</xmax>
			<ymax>561</ymax>
		</bndbox>
	</object>
	<object>
		<name>player</name>
		<pose>Unspecified</pose>
		<truncated>0</truncated>
		<difficult>0</difficult>
		<bndbox>
			<xmin>346</xmin>
			<ymin>335</ymin>
			<xmax>559</xmax>
			<ymax>470</ymax>
		</bndbox>
	</object>
	<object>
		<name>player</name>
		<pose>Unspecified</pose>
		<truncated>0</truncated>
		<difficult>0</difficult>
		<bndbox>
			<xmin>320</xmin>
			<ymin>261</ymin>
			<xmax>477</xmax>
			<ymax>384</ymax>
		</bndbox>
	</object>
	<object>
		<name>player</name>
		<pose>Unspecified</pose>
		<truncated>0</truncated>
		<difficult>0</difficult>
		<bndbox>
			<xmin>605</xmin>
			<ymin>398</ymin>
			<xmax>773</xmax>
			<ymax>563</ymax>
		</bndbox>
	</object>
	<object>
		<name>player</name>
		<pose>Unspecified</pose>
		<truncated>0</truncated>
		<difficult>0</difficult>
		<bndbox>
			<xmin>721</xmin>
			<ymin>352</ymin>
			<xmax>942</xmax>
			<ymax>550</ymax>
		</bndbox>
	</object>
	<object>
		<name>scrum</name>
		<pose>Unspecified</pose>
		<truncated>0</truncated>
		<difficult>0</difficult>
		<bndbox>
			<xmin>323</xmin>
			<ymin>235</ymin>
			<xmax>943</xmax>
			<ymax>559</ymax>
		</bndbox>
	</object>
	<object>
		<name>10_metre</name>
		<pose>Unspecified</pose>
		<truncated>1</truncated>
		<difficult>0</difficult>
		<bndbox>
			<xmin>255</xmin>
			<ymin>492</ymin>
			<xmax>954</xmax>
			<ymax>720</ymax>
		</bndbox>
	</object>
	<object>
		<name>10_metre</name>
		<pose>Unspecified</pose>
		<truncated>0</truncated>
		<difficult>0</difficult>
		<bndbox>
			<xmin>668</xmin>
			<ymin>12</ymin>
			<xmax>1263</xmax>
			<ymax>255</ymax>
		</bndbox>
	</object>
</annotation>
